{"files": ["README.md", "backend/app/__init__.py", "backend/app/app.py", "backend/app/db.py", "backend/app/models/__init__.py", "backend/app/models/crowd.py", "backend/app/routes/__init__.py", "backend/app/routes/crowd_reporting.py", "backend/app/services/crowd_service.py", "backend/app/static/css/styles.css", "backend/app/static/js/app.js", "backend/app/static/js/dashboard.js", "backend/app/static/js/map.js", "backend/app/static/js/report.js", "backend/app/templates/dashboard.html", "backend/app/templates/index.html", "backend/app/templates/map.html", "backend/app/templates/predict.html", "backend/app/templates/report.html", "backend/config/config.py", "backend/data/data.txt", "backend/requirements.txt", "prediction/app.py", "prediction/requirements.txt", "requirements.txt"], "edges": [{"source": "backend/app/app.py", "target": "backend/app/routes/crowd_reporting.py"}, {"source": "backend/app/models/crowd.py", "target": "backend/app/db.py"}, {"source": "backend/app/static/js/dashboard.js", "target": "backend/app/static/js/app.js"}, {"source": "backend/app/static/js/map.js", "target": "backend/app/static/js/report.js"}, {"source": "backend/app/static/js/report.js", "target": "backend/app/static/js/app.js"}], "root": "/Users/yechancho/repos/h-b-2026/backend/.repos/04889dccbcb2"}